TURP1210/ComponentInfoTab.py
TURP1210/GPSInterface.py
TURP1210/ISO15765.py
TURP1210/J1587Tab.py
TURP1210/J1587db.json
TURP1210/J1939Tab.py
TURP1210/J1939db.json
TURP1210/PDFReports.py
TURP1210/TU_RP1210.py
TURP1210/UserData.py
TURP1210/__init__.py
TURP1210/logging.config.json
TURP1210/micropyGPS.py
TURP1210/Graphing/__init__.py
TURP1210/Graphing/graphing.py
TURP1210/RP1210/RP1210.py
TURP1210/RP1210/RP1210Functions.py
TURP1210/RP1210/RP1210Select.py
TURP1210/RP1210/__init__.py
TURP1210/TU_crypt/TU_crypt.py
TURP1210/TU_crypt/__init__.py
TURP1210/TableModel/TableModel.py
TURP1210/TableModel/__init__.py
TURP1210/icons/Replay_48px.png
TURP1210/icons/icons8_Approval_48px_1.png
TURP1210/icons/icons8_Attention_48px_1.png
TURP1210/icons/icons8_CSV_48px.png
TURP1210/icons/icons8_C_52px.png
TURP1210/icons/icons8_C_Programming_48px.png
TURP1210/icons/icons8_Close_Window_48px.png
TURP1210/icons/icons8_Connected_48px.png
TURP1210/icons/icons8_D_52px.png
TURP1210/icons/icons8_Data_Sheet_48px.png
TURP1210/icons/icons8_Delete_Table_48px_1.png
TURP1210/icons/icons8_Dev_Post_48px.png
TURP1210/icons/icons8_Disconnected_48px.png
TURP1210/icons/icons8_Error_48px.png
TURP1210/icons/icons8_Exit_Sign_48px.png
TURP1210/icons/icons8_Export_48px_1.png
TURP1210/icons/icons8_Fingerprint_Scan_48px.png
TURP1210/icons/icons8_GPS_Disconnected_48px.png
TURP1210/icons/icons8_GPS_Signal_48px.png
TURP1210/icons/icons8_Go_48px.png
TURP1210/icons/icons8_Hand_With_Pen_48px.png
TURP1210/icons/icons8_Help_48px.png
TURP1210/icons/icons8_Help_48px_1.png
TURP1210/icons/icons8_Info_40px.png
TURP1210/icons/icons8_Line_Chart_48px.png
TURP1210/icons/icons8_M_52px.png
TURP1210/icons/icons8_More_Details_48px.png
TURP1210/icons/icons8_N_52px.png
TURP1210/icons/icons8_New_Presentation_48px.png
TURP1210/icons/icons8_New_Ticket_48px.png
TURP1210/icons/icons8_Ok_48px.png
TURP1210/icons/icons8_Open_48px_1.png
TURP1210/icons/icons8_PDF_48px.png
TURP1210-1.2.0.dist-info/DESCRIPTION.rst
TURP1210-1.2.0.dist-info/METADATA
TURP1210-1.2.0.dist-info/RECORD
TURP1210-1.2.0.dist-info/WHEEL
TURP1210-1.2.0.dist-info/entry_points.txt
TURP1210-1.2.0.dist-info/metadata.json
TURP1210-1.2.0.dist-info/top_level.txt
