Metadata-Version: 2.0
Name: TURP1210
Version: 1.2.0
Summary: A PyQt5 GUI framework for heavy vehicle diagnostic adapters using RP1210
Home-page: https://github.com/Heavy-Vehicle-Networking-At-U-Tulsa/TU-RP1210
Author: The Universtity of Tulsa, Mechanical Engineering
Author-email: jeremy-daily@utulsa.edu
License: UNKNOWN
Requires-Dist: PGPy (>=0.4.3)
Requires-Dist: PyJWT (>=1.5.3)
Requires-Dist: PyQt5 (>=5.10)
Requires-Dist: cryptography (>=2.1.4)
Requires-Dist: humanize (>=0.5.1)
Requires-Dist: matplotlib (>=2.0.2)
Requires-Dist: passlib (>=1.7.1)
Requires-Dist: pdfrw (>=0.4)
Requires-Dist: pyserial (>=3.4)
Requires-Dist: reportlab (>=3.4.0)
Requires-Dist: requests (>=2.18.4)
